<Decorations>
	<!-- Wallpapers -->	
	
	<Decoration ID="WallpaperCustomDotBlue">
        <Cost>60</Cost>
		<DecorationType>Wallpaper</DecorationType>
    </Decoration>
	<Decoration ID="WallpaperCustomHeartRed">
        <Cost>60</Cost>
		<DecorationType>Wallpaper</DecorationType>
    </Decoration>
	<Decoration ID="WallpaperCustomHoneycombYellow">
        <Cost>60</Cost>
		<DecorationType>Wallpaper</DecorationType>
    </Decoration>
	<Decoration ID="WallpaperCustomZigzagGreen">
        <Cost>60</Cost>
		<DecorationType>Wallpaper</DecorationType>
    </Decoration>
	
    <Decoration ID="WallpaperSquareGreen">
        <Cost>60</Cost>
		<DecorationType>Wallpaper</DecorationType>
    </Decoration>
    <Decoration ID="WallpaperSquareBlue">
        <Cost>60</Cost>
		<DecorationType>Wallpaper</DecorationType>
    </Decoration>
    <Decoration ID="WallpaperSquarePink">
        <Cost>60</Cost>
		<DecorationType>Wallpaper</DecorationType>
    </Decoration>
    <Decoration ID="WallpaperSquarePeach">
        <Cost>60</Cost>
		<DecorationType>Wallpaper</DecorationType>
    </Decoration>
	
    <Decoration ID="WallpaperSolidBlue">
        <Cost>30</Cost>
		<DecorationType>Wallpaper</DecorationType>
    </Decoration>
    <Decoration ID="WallpaperSolidAqua">
        <Cost>30</Cost>
		<DecorationType>Wallpaper</DecorationType>
    </Decoration>
    <Decoration ID="WallpaperSolidPink">
        <Cost>30</Cost>
		<DecorationType>Wallpaper</DecorationType>
    </Decoration>
    <Decoration ID="WallpaperSolidYellow">
        <Cost>30</Cost>
		<DecorationType>Wallpaper</DecorationType>
    </Decoration>
	
	<!-- Small Plants -->
    <Decoration ID="FlowerBulbBlue">
        <Cost>80</Cost>
		<DecorationType>SmallPlant</DecorationType>
    </Decoration>
    <Decoration ID="FlowerBulbPurple">
        <Cost>80</Cost>
		<DecorationType>SmallPlant</DecorationType>
    </Decoration>
    <Decoration ID="FlowerBulbYellow">
        <Cost>80</Cost>
		<DecorationType>SmallPlant</DecorationType>
    </Decoration>
    <Decoration ID="FlowerBulbRed">
        <Cost>80</Cost>
		<DecorationType>SmallPlant</DecorationType>
    </Decoration>	
	
	<!-- Rugs -->
    <Decoration ID="RugBlue">
        <Cost>50</Cost>
		<DecorationType>Carpet</DecorationType>
    </Decoration>	
    <Decoration ID="RugGray">
        <Cost>50</Cost>
		<DecorationType>Carpet</DecorationType>
    </Decoration>
    <Decoration ID="RugGreen">
        <Cost>50</Cost>
		<DecorationType>Carpet</DecorationType>
    </Decoration>
    <Decoration ID="RugRed">
        <Cost>50</Cost>
		<DecorationType>Carpet</DecorationType>
    </Decoration>
	<Decoration ID="RugLime">
        <Cost>50</Cost>
		<DecorationType>Carpet</DecorationType>
    </Decoration>
	
	<!-- Posters -->
	<Decoration ID="WallPoster9">
        <Cost>200</Cost>
		<DecorationType>Poster</DecorationType>
    </Decoration>
	<Decoration ID="WallPoster8">
        <Cost>200</Cost>
		<DecorationType>Poster</DecorationType>
    </Decoration>
	<Decoration ID="WallPoster7">
        <Cost>200</Cost>
		<DecorationType>Poster</DecorationType>
    </Decoration>
    <Decoration ID="WallPoster6">
        <Cost>200</Cost>
		<DecorationType>Poster</DecorationType>
    </Decoration>		
    <Decoration ID="WallPoster5">
        <Cost>200</Cost>
		<DecorationType>Poster</DecorationType>
    </Decoration>	
    <Decoration ID="WallPoster4">
        <Cost>100</Cost>
		<DecorationType>Poster</DecorationType>
    </Decoration>	
    <Decoration ID="WallPoster3">
        <Cost>100</Cost>
		<DecorationType>Poster</DecorationType>
    </Decoration>	
    <Decoration ID="WallPoster2">
        <Cost>50</Cost>
		<DecorationType>Poster</DecorationType>
    </Decoration>		
    <Decoration ID="WallPoster1">
        <Cost>50</Cost>
		<DecorationType>Poster</DecorationType>
    </Decoration>
	
</Decorations>